alibabacloud_alidns20150109/__init__.py
alibabacloud_alidns20150109/client.py
alibabacloud_alidns20150109/models/__init__.py
alibabacloud_alidns20150109/models/_add_custom_line_request.py
alibabacloud_alidns20150109/models/_add_custom_line_response.py
alibabacloud_alidns20150109/models/_add_custom_line_response_body.py
alibabacloud_alidns20150109/models/_add_dns_cache_domain_request.py
alibabacloud_alidns20150109/models/_add_dns_cache_domain_response.py
alibabacloud_alidns20150109/models/_add_dns_cache_domain_response_body.py
alibabacloud_alidns20150109/models/_add_dns_gtm_access_strategy_request.py
alibabacloud_alidns20150109/models/_add_dns_gtm_access_strategy_response.py
alibabacloud_alidns20150109/models/_add_dns_gtm_access_strategy_response_body.py
alibabacloud_alidns20150109/models/_add_dns_gtm_address_pool_request.py
alibabacloud_alidns20150109/models/_add_dns_gtm_address_pool_response.py
alibabacloud_alidns20150109/models/_add_dns_gtm_address_pool_response_body.py
alibabacloud_alidns20150109/models/_add_dns_gtm_monitor_request.py
alibabacloud_alidns20150109/models/_add_dns_gtm_monitor_response.py
alibabacloud_alidns20150109/models/_add_dns_gtm_monitor_response_body.py
alibabacloud_alidns20150109/models/_add_domain_backup_request.py
alibabacloud_alidns20150109/models/_add_domain_backup_response.py
alibabacloud_alidns20150109/models/_add_domain_backup_response_body.py
alibabacloud_alidns20150109/models/_add_domain_group_request.py
alibabacloud_alidns20150109/models/_add_domain_group_response.py
alibabacloud_alidns20150109/models/_add_domain_group_response_body.py
alibabacloud_alidns20150109/models/_add_domain_record_request.py
alibabacloud_alidns20150109/models/_add_domain_record_response.py
alibabacloud_alidns20150109/models/_add_domain_record_response_body.py
alibabacloud_alidns20150109/models/_add_domain_request.py
alibabacloud_alidns20150109/models/_add_domain_response.py
alibabacloud_alidns20150109/models/_add_domain_response_body.py
alibabacloud_alidns20150109-4.3.0.dist-info/LICENSE
alibabacloud_alidns20150109-4.3.0.dist-info/METADATA
alibabacloud_alidns20150109-4.3.0.dist-info/WHEEL
alibabacloud_alidns20150109-4.3.0.dist-info/top_level.txt
alibabacloud_alidns20150109-4.3.0.dist-info/RECORD
